MCRLLM_GUI/AllTools.py
MCRLLM_GUI/Demi_LLM_Python.py
MCRLLM_GUI/GUI.py
MCRLLM_GUI/GUI_support.py
MCRLLM_GUI/PointSelector.py
MCRLLM_GUI/Run MCR-LLM.py
MCRLLM_GUI/SI_File_Toolbox.py
MCRLLM_GUI/__init__.py
MCRLLM_GUI/cosmicRays.py
MCRLLM_GUI/dm4.py
MCRLLM_GUI/fct_H_MCR_LLM.py
MCRLLM_GUI/fct_MCRALS.py
MCRLLM_GUI/fct_MCRLLM.py
MCRLLM_GUI/fct_NMF.py
MCRLLM_GUI/fct_PCA.py
MCRLLM_GUI/fct_half_MCR.py
MCRLLM_GUI/fct_pointselector.py
MCRLLM_GUI/init.py
MCRLLM_GUI/pcaselect.py
MCRLLM_GUI-0.0.1.dist-info/METADATA
MCRLLM_GUI-0.0.1.dist-info/WHEEL
MCRLLM_GUI-0.0.1.dist-info/top_level.txt
MCRLLM_GUI-0.0.1.dist-info/RECORD
