Metadata-Version: 2.1
Name: MCRLLM-GUI
Version: 0.0.1
Summary: MCRLLM: Multivariate Curve Resolution by Log-Likelihood Maximization
Home-page: https://www.usherbrooke.ca/gchimiquebiotech/departement/professeurs/ryan-gosselin/
Author: Ryan Gosselin
Author-email: ryan.gosselin@usherbrooke.ca
License: UNKNOWN
Platform: UNKNOWN
Classifier: Programming Language :: Python :: 3
Classifier: License :: OSI Approved :: MIT License
Classifier: Operating System :: OS Independent
